Metadata-Version: 2.4
Name: ml2sql
Version: 0.1.10
Summary: Automated interpretable ML tool with SQL version of model
Author-email: Kasper de <kasperde@hotmail.com>
License: MIT License
Project-URL: Homepage, https://github.com/kaspersgit/ml_2_sql
Project-URL: Issues, https://github.com/kaspersgit/ml_2_sql/issues
Keywords: SQL,ML,automl,interpret,ML 2 SQL,EBM,Explainable Boosting Machine,ML to SQL
Classifier: Programming Language :: Python :: 3
Classifier: License :: OSI Approved :: MIT License
Classifier: Operating System :: OS Independent
Requires-Python: >=3.8
License-File: LICENSE
Requires-Dist: interpret==0.6.3
Requires-Dist: numpy~=1.24.4
Requires-Dist: duckdb~=1.2.1
Requires-Dist: scikit-learn~=1.3.2
Requires-Dist: imblearn
Requires-Dist: kaleido==0.2.0
Requires-Dist: typer~=0.15.2
Requires-Dist: pywin32; platform_system == "Windows"
Requires-Dist: pytest~=8.3.5
Provides-Extra: dev
Requires-Dist: pytest; extra == "dev"
Requires-Dist: pytest-mock; extra == "dev"
Requires-Dist: pip-tools; extra == "dev"
Requires-Dist: ruff; extra == "dev"
Requires-Dist: pre-commit; extra == "dev"
Requires-Dist: coverage; extra == "dev"
Dynamic: license-file
